witenc/__init__.py
witenc/bls.py
witenc/chianetbls/bls12381.py
witenc/chianetbls/ec.py
witenc/chianetbls/fields.py
witenc/chianetbls/hash_to_field.py
witenc/chianetbls/hd_keys.py
witenc/chianetbls/hkdf.py
witenc/chianetbls/op_swu_g2.py
witenc/chianetbls/pairing.py
witenc/chianetbls/private_key.py
witenc/chianetbls/schemes.py
witenc/chianetbls/util.py
witenc/groups.py
witenc/utils.py
witenc/witenc.py
witenc-0.1.1.dist-info/LICENSE
witenc-0.1.1.dist-info/METADATA
witenc-0.1.1.dist-info/WHEEL
witenc-0.1.1.dist-info/RECORD
