Metadata-Version: 2.1
Name: witenc
Version: 0.1.1
Summary: Implements a signature based witness encryption scheme based on the BLS signatures
License: Apache-2.0
Author: David L. Adei
Author-email: lokingdav@gmail.com
Requires-Python: >=3.8,<4.0
Classifier: License :: OSI Approved :: Apache Software License
Classifier: Programming Language :: Python :: 3
Classifier: Programming Language :: Python :: 3.8
Classifier: Programming Language :: Python :: 3.9
Classifier: Programming Language :: Python :: 3.10
Classifier: Programming Language :: Python :: 3.11
